{
   "person": [
       {
           "number": 1,
           "t" : "이거 뭐에요?",
           "writer" : "낫휴먼",
           "date" : "2020-06-10",
           "hit" : 3
       },
       {
           "number": 2,
           "t" : "hello",
           "writer" : "tom",
           "date" : "2020-06-10",
           "hit" : 2
       },{
           "number": 3,
           "t" : "^^",
           "writer" : ":)",
           "date" : "2020-06-10",
           "hit" : 10
       },{
           "number": 4,
           "t" : "종강언제해?",
           "writer" : "공대생",
           "date" : "2020-06-10",
           "hit" : 3
       },{
           "number": 5,
           "t" : "ㅇㅇ",
           "writer" : "ㅇ_ㅇ",
           "date" : "2020-06-10",
           "hit" : 10
       },{
           "number": 6,
           "t" : "이거 뭐에요?",
           "writer" : "낫휴먼",
           "date" : "2020-06-10",
           "hit" : 4
       }
   ]
}